salesplansuccess
